datacamprojects-0.0.1.dist-info/METADATA
datacamprojects-0.0.1.dist-info/RECORD
datacamprojects-0.0.1.dist-info/WHEEL
datacamprojects-0.0.1.dist-info/entry_points.txt
datacamprojects-0.0.1.dist-info/top_level.txt
src/__init__.py
src/__main__.py
src/datecamp.py
src/pipeline.py
