Metadata-Version: 2.1
Name: datacamprojects
Version: 0.0.1
Summary: Tools for the DataCamp Creating Robust Python Projects course
Home-page: https://github.com/marskar/datacamprojects
Author: Martin Skarzynski
Author-email: marskar@gmail.com
License: UNKNOWN
Platform: UNKNOWN
Classifier: Programming Language :: Python :: 3
Classifier: License :: OSI Approved :: MIT License
Classifier: Operating System :: OS Independent
Requires-Dist: scikit-learn
Requires-Dist: matplotlib
Requires-Dist: seaborn
